{
    "Monday" : { 
       "user1": [
            "8PM dinner"
        ] 
    },

    "Tuesday" : {
        "user1": [
            "9AM Soccor Game"
        ],
        "user2": [
            "12PM hangout with friends"

        ]
         
    },
    
    "Wednesday" : {
        "user1": [
            "11pm Soccor Game"
         
        ],
        "user2": [
            "12PM hangout with friends breakfast",
            "12PM sport",
            "12PM school",
            "12PM hangout",
            "12PM zoo"


        ]
         
    },

    "Thursday" : {
         
    },

    "Friday" : {
     
         
    },

    "Saturday" : {
      
         
    },

    "Sunday" : {
         
    }

}
